pkns/Serializer.py
pkns/Signing.py
pkns/__init__.py
pkns/cli.py
pkns/pknscore.py
pkns-0.5.12.dist-info/entry_points.txt
pkns-0.5.12.dist-info/LICENSE
pkns-0.5.12.dist-info/WHEEL
pkns-0.5.12.dist-info/METADATA
pkns-0.5.12.dist-info/RECORD
