Metadata-Version: 2.1
Name: pkns
Version: 0.5.12
Summary: Public Key Name System Framework
Home-page: https://github.com/anubhav-narayan/PKNS
License: AGPL-3.0-or-later
Author: Anubhav Mattoo
Author-email: anubhavmattoo@outlook.com
Requires-Python: >=3.6,<4.0
Classifier: Development Status :: 4 - Beta
Classifier: Intended Audience :: Developers
Classifier: License :: OSI Approved :: GNU Affero General Public License v3
Classifier: License :: OSI Approved :: GNU Affero General Public License v3 or later (AGPLv3+)
Classifier: Operating System :: POSIX :: Linux
Classifier: Programming Language :: Python :: 3
Classifier: Programming Language :: Python :: 3.6
Classifier: Programming Language :: Python :: 3.7
Classifier: Programming Language :: Python :: 3.8
Classifier: Programming Language :: Python :: 3.9
Classifier: Topic :: Communications
Classifier: Topic :: Internet
Classifier: Topic :: Security :: Cryptography
Requires-Dist: click (>=8.0.1,<9.0.0)
Requires-Dist: daemonocle (>=1.2.3,<2.0.0)
Requires-Dist: dill (>=0.3.3,<0.4.0)
Requires-Dist: pickle5 (>=0.0.11,<0.0.12)
Requires-Dist: pycryptodome (>=3.10.1,<4.0.0)
Requires-Dist: sqlitedict (==1.7.0)
Project-URL: Bug Tracker, https://github.com/anubhav-narayan/PKNS/issues
Project-URL: Repository, https://github.com/anubhav-narayan/PKNS
